[
  {
      "ID": "67f32d25c689547e8bb3eb45",
      "Name": "Apple",
      "Description": "",
      "ManufacturerID": "67f00c6b2916d65ec486c56d",
      "MetaKeywords": "",
      "MetaDescription": "",
      "MetaTitle": "",
      "PictureID": "67f32682fc045cc4345830b1",
      "PageSize": 6,
      "AllowCustomersToSelectPageSize": true,
      "PageSizeOptions": "6, 3, 9",
      "SubjectToAcl": false,
      "LimitedToStores": false,
      "Published": true,
      "Deleted": false,
      "DisplayOrder": 1,
      "CreatedOnUtc": "2025-04-01T00:00:00Z",
      "UpdatedOnUtc": "2025-04-05T00:00:00Z",
      "PriceRangeFiltering": true,
      "PriceFrom": 0,
      "PriceTo": 10000,
      "ManuallyPriceRange": true
  },
  {
      "ID": "67f32d25c689547e8bb3eb46",
      "Name": "HP",
      "Description": "",
      "ManufacturerID": "67f00c6b2916d65ec486c56d",
      "MetaKeywords": "",
      "MetaDescription": "",
      "MetaTitle": "",
      "PictureID": "67f32682fc045cc4345830b2",
      "PageSize": 6,
      "AllowCustomersToSelectPageSize": true,
      "PageSizeOptions": "6, 3, 9",
      "SubjectToAcl": false,
      "LimitedToStores": false,
      "Published": true,
      "Deleted": false,
      "DisplayOrder": 5,
      "CreatedOnUtc": "2025-04-01T00:00:00Z",
      "UpdatedOnUtc": "2025-04-05T00:00:00Z",
      "PriceRangeFiltering": true,
      "PriceFrom": 0,
      "PriceTo": 10000,
      "ManuallyPriceRange": true
  },
  {
      "ID": "67f32d25c689547e8bb3eb47",
      "Name": "Nike",
      "Description": "",
      "ManufacturerID": "67f00c6b2916d65ec486c56d",
      "MetaKeywords": "",
      "MetaDescription": "",
      "MetaTitle": "",
      "PictureID": "67f32682fc045cc4345830b3",
      "PageSize": 6,
      "AllowCustomersToSelectPageSize": true,
      "PageSizeOptions": "6, 3, 9",
      "SubjectToAcl": false,
      "LimitedToStores": false,
      "Published": true,
      "Deleted": false,
      "DisplayOrder": 10,
      "CreatedOnUtc": "2025-04-01T00:00:00Z",
      "UpdatedOnUtc": "2025-04-05T00:00:00Z",
      "PriceRangeFiltering": true,
      "PriceFrom": 0,
      "PriceTo": 10000,
      "ManuallyPriceRange": true
  }
]